django_graph_api/__init__.py
django_graph_api/views.py
django_graph_api/graphql/__init__.py
django_graph_api/graphql/ast_helpers.py
django_graph_api/graphql/introspection.py
django_graph_api/graphql/request.py
django_graph_api/graphql/schema.py
django_graph_api/graphql/types.py
django_graph_api/graphql/utils.py
django_graph_api/graphql/validation.py
django_graph_api/templates/django_graph_api/graphiql.html
django_graph_api/tests/__init__.py
django_graph_api/tests/conftest.py
django_graph_api/tests/test_arguments.py
django_graph_api/tests/test_basic.py
django_graph_api/tests/test_errors.py
django_graph_api/tests/test_fragments.py
django_graph_api/tests/test_introspection.py
django_graph_api/tests/test_schema.py
django_graph_api/tests/test_variables.py
django_graph_api/tests/test_views.py
django_graph_api/tests/validation/__init__.py
django_graph_api/tests/validation/test_arguments.py
django_graph_api/tests/validation/test_basic.py
django_graph_api/tests/validation/test_operations.py
django_graph_api-0.3.0.dist-info/METADATA
django_graph_api-0.3.0.dist-info/RECORD
django_graph_api-0.3.0.dist-info/WHEEL
django_graph_api-0.3.0.dist-info/top_level.txt
