Metadata-Version: 2.1
Name: django-graph-api
Version: 0.3.0
Summary: A Python implementation of GraphQL designed for use with Django
Home-page: http://django-graph-api.readthedocs.io/
Author: Stephen Burrows
Author-email: stephen.r.burrows@gmail.com
License: UNKNOWN
Download-URL: https://github.com/django-graph-api/django-graph-api
Platform: UNKNOWN
Classifier: Development Status :: 1 - Planning
Classifier: Intended Audience :: Developers
Classifier: Topic :: Software Development :: Libraries
Classifier: License :: OSI Approved :: MIT License
Classifier: Natural Language :: English
Classifier: Environment :: Web Environment
Classifier: Programming Language :: Python
Classifier: Programming Language :: Python :: 2.7
Classifier: Programming Language :: Python :: 3.5
Classifier: Programming Language :: Python :: 3.6
Classifier: Framework :: Django :: 1.11
Requires-Dist: django (>=1.8)
Requires-Dist: graphql-py (>=0.6)
